<?xml version="1.0" encoding="UTF-8"?>
<objects serializationModel="Studio.02.02.00">
	<object class="AudioFile" id="{b070014e-4355-409e-bbe9-71cbfa014fc0}">
		<property name="assetPath">
			<value>z_placeholders/sx_placeholder/sx_robotvoice_number_03.wav</value>
		</property>
		<property name="frequencyInKHz">
			<value>48</value>
		</property>
		<property name="channelCount">
			<value>2</value>
		</property>
		<property name="length">
			<value>0.47202083333333333</value>
		</property>
		<relationship name="masterAssetFolder">
			<destination>{859b5e87-24c7-48e8-8580-c988882a6199}</destination>
		</relationship>
	</object>
</objects>
